{
  "type": "FeatureCollection",
  "features": [
    {
      "type": "Feature",
      "geometry": {
        "type": "Polygon",
        "coordinates": [
          [
            [
              114.1962786255369,
              22.54324621293982
            ],
            [
              114.16446785884182,
              22.54324621293982
            ],
            [
              114.16446785884182,
              22.56417922281605
            ],
            [
              114.1962786255369,
              22.56417922281605
            ],
            [
              114.1962786255369,
              22.54324621293982
            ]
          ]
        ]
      },
      "properties": {
        "species_name": "Misgurnus anguillicaudatus",
        "prediction_year": 2025,
        "prediction_id": 1,
        "feature_type": "grid_box",
        "likelihood": 1.0
      }
    },
    {
      "type": "Feature",
      "geometry": {
        "type": "Polygon",
        "coordinates": [
          [
            [
              114.19626692998817,
              22.45951642358917
            ],
            [
              114.16447531384645,
              22.45951642358917
            ],
            [
              114.16447531384645,
              22.48044964854685
            ],
            [
              114.19626692998817,
              22.48044964854685
            ],
            [
              114.19626692998817,
              22.45951642358917
            ]
          ]
        ]
      },
      "properties": {
        "species_name": "Misgurnus anguillicaudatus",
        "prediction_year": 2025,
        "prediction_id": 2,
        "feature_type": "grid_box",
        "likelihood": 1.0
      }
    },
    {
      "type": "Feature",
      "geometry": {
        "type": "Polygon",
        "coordinates": [
          [
            [
              114.3551886292371,
              22.438486510007362
            ],
            [
              114.32342578662868,
              22.438486510007362
            ],
            [
              114.32342578662868,
              22.45945100627484
            ],
            [
              114.3551886292371,
              22.45945100627484
            ],
            [
              114.3551886292371,
              22.438486510007362
            ]
          ]
        ]
      },
      "properties": {
        "species_name": "Misgurnus anguillicaudatus",
        "prediction_year": 2025,
        "prediction_id": 3,
        "feature_type": "grid_box",
        "likelihood": 1.0
      }
    }
  ],
  "prediction_info": {
    "species_name": "Misgurnus anguillicaudatus",
    "predicted_locations": 3,
    "model_type": "Neural Network (Cached)",
    "prediction_year": 2025
  }
}