{
  "type": "FeatureCollection",
  "features": [
    {
      "type": "Feature",
      "geometry": {
        "type": "Polygon",
        "coordinates": [
          [
            [
              114.19626110164926,
              22.417651204122716
            ],
            [
              114.16447902684425,
              22.417651204122716
            ],
            [
              114.16447902684425,
              22.438584536384546
            ],
            [
              114.19626110164926,
              22.438584536384546
            ],
            [
              114.19626110164926,
              22.417651204122716
            ]
          ]
        ]
      },
      "properties": {
        "species_name": "Rhabdophis subminiatus helleri",
        "prediction_year": 2025,
        "prediction_id": 1,
        "feature_type": "grid_box",
        "likelihood": 1.0
      }
    },
    {
      "type": "Feature",
      "geometry": {
        "type": "Polygon",
        "coordinates": [
          [
            [
              114.16448826713491,
              22.33392081052491
            ],
            [
              114.13272046920216,
              22.33392081052491
            ],
            [
              114.13272046920216,
              22.35484812625191
            ],
            [
              114.16448826713491,
              22.35484812625191
            ],
            [
              114.16448826713491,
              22.33392081052491
            ]
          ]
        ]
      },
      "properties": {
        "species_name": "Rhabdophis subminiatus helleri",
        "prediction_year": 2025,
        "prediction_id": 2,
        "feature_type": "grid_box",
        "likelihood": 1.0
      }
    },
    {
      "type": "Feature",
      "geometry": {
        "type": "Polygon",
        "coordinates": [
          [
            [
              113.91059786552002,
              22.229038341516034
            ],
            [
              113.87881646135558,
              22.229038341516034
            ],
            [
              113.87881646135558,
              22.249916137920565
            ],
            [
              113.91059786552002,
              22.249916137920565
            ],
            [
              113.91059786552002,
              22.229038341516034
            ]
          ]
        ]
      },
      "properties": {
        "species_name": "Rhabdophis subminiatus helleri",
        "prediction_year": 2025,
        "prediction_id": 3,
        "feature_type": "grid_box",
        "likelihood": 1.0
      }
    }
  ],
  "prediction_info": {
    "species_name": "Rhabdophis subminiatus helleri",
    "predicted_locations": 3,
    "model_type": "Neural Network (Cached)",
    "prediction_year": 2025
  }
}